gpycat/__init__.py
gpycat/core.py
gpycat/models/__init__.py
gpycat/models/album.py
gpycat/models/gfy_item.py
gpycat/session.py
gpycat-0.1.3.dist-info/LICENSE
gpycat-0.1.3.dist-info/METADATA
gpycat-0.1.3.dist-info/WHEEL
gpycat-0.1.3.dist-info/RECORD
