Metadata-Version: 2.1
Name: gpycat
Version: 0.1.3
Summary: Python Gfycat API
Home-page: https://github.com/kvdomingo/pygfycat
Author: Kenneth V. Domingo
Author-email: hello@kvdomingo.xyz
Requires-Python: >=3.8,<3.11
Classifier: Development Status :: 2 - Pre-Alpha
Classifier: Intended Audience :: Developers
Classifier: License :: OSI Approved :: MIT License
Classifier: Programming Language :: Python :: 3
Classifier: Programming Language :: Python :: 3.8
Classifier: Programming Language :: Python :: 3.9
Classifier: Programming Language :: Python :: 3.10
Classifier: Topic :: Software Development :: Libraries :: Python Modules
Classifier: Typing :: Typed
Requires-Dist: coverage-badge (>=1.1.0,<2.0.0)
Requires-Dist: loguru (>=0.6.0,<0.7.0)
Requires-Dist: pydantic (>=1.9.2,<2.0.0)
Requires-Dist: requests (>=2.28.1,<3.0.0)
Requires-Dist: requests-toolbelt (>=0.9.1,<0.10.0)
